<ManipulationObject name='ManipulationObject'>
	<Visualization>
		<File type='inventor'>../../data/perdurbation/../ramcip_objects/xml/../wrl/depon.wrl</File>
	</Visualization>
	<CollisionModel>
		<File type='inventor'>../../data/perdurbation/../ramcip_objects/xml/../wrl/depon.wrl</File>
	</CollisionModel>
	<GraspSet name='Grasp Planner - SHADOWHAND' RobotType='SHADOWHAND' EndEffector='SHADOWHAND'>
		<Grasp name='Grasp 1' quality='0.557227' Creation='Simox - GraspStudio - GraspWrenchSpace' Preshape='Grasp Preshape'>
			<Transform>
				<Matrix4x4>
					<row1 c1='-0.778577' c2='-0.478945' c3='0.4055' c4='-22.6747'/>
					<row2 c1='0.298151' c2='-0.85089' c3='-0.43254' c4='8.78312'/>
					<row3 c1='0.552199' c2='-0.215865' c3='0.805282' c4='148.844'/>
					<row4 c1='0' c2='0' c3='0' c4='1'/>
				</Matrix4x4>
			</Transform>
			<Configuration name='Grasp 1'>
				<Node name='H1_F1J1' unit='radian' value='-0.110797'/>
				<Node name='H1_F1J2' unit='radian' value='1.013'/>
				<Node name='H1_F2J1' unit='radian' value='-0.310797'/>
				<Node name='H1_F2J2' unit='radian' value='1.553'/>
				<Node name='H1_F3J1' unit='radian' value='-0.290797'/>
				<Node name='H1_F3J2' unit='radian' value='1.173'/>
			</Configuration>
		</Grasp>
		<Grasp name='Grasp 2' quality='0.595843' Creation='Simox - GraspStudio - GraspWrenchSpace' Preshape='Grasp Preshape'>
			<Transform>
				<Matrix4x4>
					<row1 c1='-0.69309' c2='0.34255' c3='-0.634261' c4='-8.77559'/>
					<row2 c1='0.467362' c2='-0.456351' c3='-0.757176' c4='-3.67678'/>
					<row3 c1='-0.548816' c2='-0.821221' c3='0.156197' c4='139.318'/>
					<row4 c1='0' c2='0' c3='0' c4='1'/>
				</Matrix4x4>
			</Transform>
			<Configuration name='Grasp 2'>
				<Node name='H1_F1J1' unit='radian' value='0.149203'/>
				<Node name='H1_F1J2' unit='radian' value='0.652999'/>
				<Node name='H1_F2J1' unit='radian' value='-0.750797'/>
				<Node name='H1_F2J2' unit='radian' value='1.353'/>
				<Node name='H1_F3J1' unit='radian' value='-1.2708'/>
				<Node name='H1_F3J2' unit='radian' value='1.553'/>
			</Configuration>
		</Grasp>
		<Grasp name='Grasp 3' quality='0.500963' Creation='Simox - GraspStudio - GraspWrenchSpace' Preshape='Grasp Preshape'>
			<Transform>
				<Matrix4x4>
					<row1 c1='-0.832742' c2='-0.189397' c3='0.520259' c4='29.2249'/>
					<row2 c1='-0.0402117' c2='0.957879' c3='0.284345' c4='-28.4101'/>
					<row3 c1='-0.552199' c2='0.215865' c3='-0.805282' c4='150.656'/>
					<row4 c1='0' c2='0' c3='0' c4='1'/>
				</Matrix4x4>
			</Transform>
			<Configuration name='Grasp 3'>
				<Node name='H1_F1J1' unit='radian' value='0.329203'/>
				<Node name='H1_F1J2' unit='radian' value='0.892999'/>
				<Node name='H1_F2J1' unit='radian' value='-1.2308'/>
				<Node name='H1_F2J2' unit='radian' value='1.473'/>
				<Node name='H1_F3J1' unit='radian' value='-0.830797'/>
				<Node name='H1_F3J2' unit='radian' value='1.553'/>
			</Configuration>
		</Grasp>
		<Grasp name='Grasp 4' quality='0.576125' Creation='Simox - GraspStudio - GraspWrenchSpace' Preshape='Grasp Preshape'>
			<Transform>
				<Matrix4x4>
					<row1 c1='-0.833664' c2='-0.132599' c3='0.536117' c4='8.88068'/>
					<row2 c1='0.00895' c2='0.967378' c3='0.25318' c4='8.15936'/>
					<row3 c1='-0.552199' c2='0.215865' c3='-0.805282' c4='150.656'/>
					<row4 c1='0' c2='0' c3='0' c4='1'/>
				</Matrix4x4>
			</Transform>
			<Configuration name='Grasp 4'>
				<Node name='H1_F1J1' unit='radian' value='-0.190797'/>
				<Node name='H1_F1J2' unit='radian' value='0.972999'/>
				<Node name='H1_F2J1' unit='radian' value='-0.210797'/>
				<Node name='H1_F2J2' unit='radian' value='0.353'/>
				<Node name='H1_F3J1' unit='radian' value='-1.0308'/>
				<Node name='H1_F3J2' unit='radian' value='1.553'/>
			</Configuration>
		</Grasp>
		<Grasp name='Grasp 5' quality='0.577851' Creation='Simox - GraspStudio - GraspWrenchSpace' Preshape='Grasp Preshape'>
			<Transform>
				<Matrix4x4>
					<row1 c1='0.778337' c2='0.40896' c3='0.476386' c4='9.64626'/>
					<row2 c1='0.0177251' c2='0.744146' c3='-0.667782' c4='12.4535'/>
					<row3 c1='-0.627596' c2='0.528203' c3='0.571947' c4='146.434'/>
					<row4 c1='0' c2='0' c3='0' c4='1'/>
				</Matrix4x4>
			</Transform>
			<Configuration name='Grasp 5'>
				<Node name='H1_F1J1' unit='radian' value='-0.190797'/>
				<Node name='H1_F1J2' unit='radian' value='0.612999'/>
				<Node name='H1_F2J1' unit='radian' value='-1.0908'/>
				<Node name='H1_F2J2' unit='radian' value='1.553'/>
				<Node name='H1_F3J1' unit='radian' value='-0.150797'/>
				<Node name='H1_F3J2' unit='radian' value='0.393'/>
			</Configuration>
		</Grasp>
		<Grasp name='Grasp 6' quality='0.627051' Creation='Simox - GraspStudio - GraspWrenchSpace' Preshape='Grasp Preshape'>
			<Transform>
				<Matrix4x4>
					<row1 c1='-0.356081' c2='-0.848047' c3='0.392459' c4='3.41802'/>
					<row2 c1='0.692336' c2='0.0426464' c3='0.720314' c4='0.832538'/>
					<row3 c1='-0.627596' c2='0.528203' c3='0.571947' c4='155.434'/>
					<row4 c1='0' c2='0' c3='0' c4='1'/>
				</Matrix4x4>
			</Transform>
			<Configuration name='Grasp 6'>
				<Node name='H1_F1J1' unit='radian' value='-1.3508'/>
				<Node name='H1_F1J2' unit='radian' value='1.553'/>
				<Node name='H1_F2J1' unit='radian' value='-0.490797'/>
				<Node name='H1_F2J2' unit='radian' value='0.212999'/>
				<Node name='H1_F3J1' unit='radian' value='-0.0107973'/>
				<Node name='H1_F3J2' unit='radian' value='1.553'/>
			</Configuration>
		</Grasp>
		<Grasp name='Grasp 7' quality='0.552048' Creation='Simox - GraspStudio - GraspWrenchSpace' Preshape='Grasp Preshape'>
			<Transform>
				<Matrix4x4>
					<row1 c1='-0.490796' c2='0.301852' c3='-0.817316' c4='2.38743'/>
					<row2 c1='-0.604352' c2='-0.793654' c3='0.0697985' c4='-1.09392'/>
					<row3 c1='-0.627596' c2='0.528203' c3='0.571947' c4='164.434'/>
					<row4 c1='0' c2='0' c3='0' c4='1'/>
				</Matrix4x4>
			</Transform>
			<Configuration name='Grasp 7'>
				<Node name='H1_F1J1' unit='radian' value='-0.230797'/>
				<Node name='H1_F1J2' unit='radian' value='0.293'/>
				<Node name='H1_F2J1' unit='radian' value='-0.0907973'/>
				<Node name='H1_F2J2' unit='radian' value='0.453'/>
				<Node name='H1_F3J1' unit='radian' value='-0.810797'/>
				<Node name='H1_F3J2' unit='radian' value='1.493'/>
			</Configuration>
		</Grasp>
		<Grasp name='Grasp 8' quality='0.593855' Creation='Simox - GraspStudio - GraspWrenchSpace' Preshape='Grasp Preshape'>
			<Transform>
				<Matrix4x4>
					<row1 c1='-0.496686' c2='-0.837364' c3='0.228308' c4='-10.9494'/>
					<row2 c1='0.599522' c2='-0.140793' c3='0.787878' c4='-2.36663'/>
					<row3 c1='-0.627596' c2='0.528203' c3='0.571947' c4='152.434'/>
					<row4 c1='0' c2='0' c3='0' c4='1'/>
				</Matrix4x4>
			</Transform>
			<Configuration name='Grasp 8'>
				<Node name='H1_F1J1' unit='radian' value='-1.4308'/>
				<Node name='H1_F1J2' unit='radian' value='1.553'/>
				<Node name='H1_F2J1' unit='radian' value='-0.470797'/>
				<Node name='H1_F2J2' unit='radian' value='0.553'/>
				<Node name='H1_F3J1' unit='radian' value='-0.250797'/>
				<Node name='H1_F3J2' unit='radian' value='0.872999'/>
			</Configuration>
		</Grasp>
		<Grasp name='Grasp 9' quality='0.575971' Creation='Simox - GraspStudio - GraspWrenchSpace' Preshape='Grasp Preshape'>
			<Transform>
				<Matrix4x4>
					<row1 c1='0.831399' c2='0.214486' c3='-0.512612' c4='7.92625'/>
					<row2 c1='0.0620661' c2='-0.952574' c3='-0.297909' c4='1.23056'/>
					<row3 c1='-0.552199' c2='0.215865' c3='-0.805282' c4='147.656'/>
					<row4 c1='0' c2='0' c3='0' c4='1'/>
				</Matrix4x4>
			</Transform>
			<Configuration name='Grasp 9'>
				<Node name='H1_F1J1' unit='radian' value='0.00920272'/>
				<Node name='H1_F1J2' unit='radian' value='0.712999'/>
				<Node name='H1_F2J1' unit='radian' value='-1.3508'/>
				<Node name='H1_F2J2' unit='radian' value='1.553'/>
				<Node name='H1_F3J1' unit='radian' value='-0.330797'/>
				<Node name='H1_F3J2' unit='radian' value='0.373'/>
			</Configuration>
		</Grasp>
		<Grasp name='Grasp 10' quality='0.536569' Creation='Simox - GraspStudio - GraspWrenchSpace' Preshape='Grasp Preshape'>
			<Transform>
				<Matrix4x4>
					<row1 c1='0.0957634' c2='-0.676689' c3='0.730015' c4='20.006'/>
					<row2 c1='0.772627' c2='0.512927' c3='0.374105' c4='-43.3996'/>
					<row3 c1='-0.627596' c2='0.528203' c3='0.571947' c4='167.434'/>
					<row4 c1='0' c2='0' c3='0' c4='1'/>
				</Matrix4x4>
			</Transform>
			<Configuration name='Grasp 10'>
				<Node name='H1_F1J1' unit='radian' value='0.269203'/>
				<Node name='H1_F1J2' unit='radian' value='0.812999'/>
				<Node name='H1_F2J1' unit='radian' value='-0.990797'/>
				<Node name='H1_F2J2' unit='radian' value='0.533'/>
				<Node name='H1_F3J1' unit='radian' value='0.329203'/>
				<Node name='H1_F3J2' unit='radian' value='1.553'/>
			</Configuration>
		</Grasp>
	</GraspSet>

</ManipulationObject>
